Metadata-Version: 2.1
Name: feast-snowflake
Version: 0.1.7
Summary: Snowflake offline store for Feast
Home-page: https://github.com/sfc-gh-madkins/feast-snowflake
Author: Miles Adkins
Author-email: miles.adkins@snowflake.com
License: Apache License, Version 2.0
Project-URL: Bug Tracker, https://github.com/sfc-gh-madkins/feast-snowflake/issues
Keywords: feast featurestore snowflake offlinestore
Platform: UNKNOWN
Classifier: License :: OSI Approved :: Apache Software License
Classifier: Programming Language :: Python
Classifier: Programming Language :: Python :: 3
Classifier: Programming Language :: Python :: 3.7
Requires-Python: >=3.7.0
License-File: LICENSE
